{
  "title": "mukta-sticky-cards-nextjs",
  "code": {
    "jsconfig.json": "{\n  \"compilerOptions\": {\n    \"paths\": {\n      \"@/*\": [\"./src/*\"]\n    }\n  }\n}\n",
    "next.config.mjs": "/** @type {import('next').NextConfig} */\nconst nextConfig = {};\n\nexport default nextConfig;\n",
    "package.json": "{\n  \"name\": \"mukta-sticky-cards-nextjs\",\n  \"version\": \"0.1.0\",\n  \"private\": true,\n  \"scripts\": {\n    \"dev\": \"next dev\",\n    \"build\": \"next build\",\n    \"start\": \"next start\"\n  },\n  \"dependencies\": {\n    \"@gsap/react\": \"^2.1.2\",\n    \"gsap\": \"^3.13.0\",\n    \"lenis\": \"^1.3.11\",\n    \"next\": \"15.5.2\",\n    \"react\": \"19.1.0\",\n    \"react-dom\": \"19.1.0\"\n  }\n}\n",
    "src/app/globals.css": "@import url(\"https://fonts.googleapis.com/css2?family=Manrope:wght@200..800&display=swap\");\n\n:root {\n  --bg: #1a1a1a;\n  --fg: #edf1e8;\n}\n\n* {\n  margin: 0;\n  padding: 0;\n  box-sizing: border-box;\n}\n\nbody {\n  font-family: \"Manrope\", sans-serif;\n  background-color: #000;\n}\n\nimg {\n  width: 100%;\n  height: 100%;\n  object-fit: cover;\n}\n\nh1 {\n  font-size: 7rem;\n  font-weight: 800;\n  letter-spacing: -0.35rem;\n  line-height: 1.1;\n}\n\np {\n  font-size: 1.125rem;\n  font-weight: 500;\n}\n\nsection {\n  position: relative;\n  width: 100%;\n  height: 100svh;\n  background-color: var(--bg);\n  color: var(--fg);\n  display: flex;\n  justify-content: center;\n  align-items: center;\n  text-align: center;\n}\n\n@media (max-width: 1000px) {\n  h1 {\n    font-size: 2rem;\n    letter-spacing: 0;\n  }\n\n  p {\n    font-size: 1rem;\n  }\n}\n",
    "src/app/layout.js": "import \"./globals.css\";\n\nexport const metadata = {\n  title: \"OH Architecture Sticky Cards | mukta\",\n  description: \"OH Architecture Sticky Cards | mukta\",\n};\n\nexport default function RootLayout({ children }) {\n  return (\n    <html lang=\"en\">\n      <body>{children}</body>\n    </html>\n  );\n}\n",
    "src/app/page.js": "import { ReactLenis } from \"lenis/react\";\nimport StickyCards from \"@/components/StickyCards/StickyCards\";\n\nexport default function Home() {\n  return (\n    <>\n      <ReactLenis root />\n      <section className=\"intro\">\n        <h1>The Foundations</h1>\n      </section>\n\n      <StickyCards />\n\n      <section className=\"outro\">\n        <h1>Ends in Form</h1>\n      </section>\n    </>\n  );\n}\n",
    "src/app/page.module.css": "",
    "src/components/StickyCards/StickyCards.css": ".sticky-cards {\n  position: relative;\n  width: 100%;\n  height: 100%;\n  background-color: var(--bg);\n}\n\n.sticky-card {\n  position: relative;\n  width: 100%;\n  height: 100svh;\n  background-color: var(--fg);\n  color: var(--bg);\n  padding: 1.5rem;\n  display: flex;\n  gap: 3rem;\n  will-change: transform;\n}\n\n.sticky-card::after {\n  content: \"\";\n  position: absolute;\n  top: 0;\n  left: 0;\n  width: 100%;\n  height: 100%;\n  background-color: rgba(0, 0, 0, 0.5);\n  opacity: var(--after-opacity, 0);\n  transition: opacity 0.1s ease;\n  pointer-events: none;\n  z-index: 2;\n}\n\n.sticky-card-index {\n  flex: 2;\n}\n\n.sticky-card-content {\n  flex: 4;\n  padding-top: 1.5rem;\n}\n\n.sticky-card-content-wrapper {\n  width: 75%;\n  display: flex;\n  flex-direction: column;\n  gap: 1.5rem;\n}\n\n.sticky-card-header {\n  width: 75%;\n}\n\n.sticky-card-img img {\n  aspect-ratio: 5/3;\n}\n\n.sticky-card-copy {\n  display: flex;\n  gap: 1.5rem;\n}\n\n.sticky-card-copy-title {\n  flex: 2;\n}\n\n.sticky-card-copy-description {\n  flex: 4;\n}\n\n.sticky-card-copy-title p {\n  text-transform: uppercase;\n  font-weight: 650;\n}\n\n@media (max-width: 1000px) {\n  .sticky-card {\n    flex-direction: column;\n    gap: 0;\n  }\n\n  .sticky-card-content-wrapper {\n    width: 100%;\n  }\n\n  .sticky-card-copy {\n    flex-direction: column;\n    gap: 0.5rem;\n  }\n\n  .sticky-card-index {\n    flex: 1;\n  }\n}\n",
    "src/components/StickyCards/StickyCards.jsx": "\"use client\";\nimport \"./StickyCards.css\";\n\nimport { useRef } from \"react\";\n\nimport gsap from \"gsap\";\nimport { ScrollTrigger } from \"gsap/ScrollTrigger\";\nimport { useGSAP } from \"@gsap/react\";\n\ngsap.registerPlugin(ScrollTrigger);\n\nconst StickyCards = () => {\n  const stickyCardsData = [\n    {\n      index: \"01\",\n      title: \"Modularity\",\n      image: \"/sticky-cards/card_1.jpg\",\n      description:\n        \"Every element is built to snap into place. We design modular systems where clarity, structure, and reuse come first—no clutter, no excess.\",\n    },\n    {\n      index: \"02\",\n      title: \"Materials\",\n      image: \"/sticky-cards/card_2.jpg\",\n      description:\n        \"From soft gradients to hard edges, our design language draws from real-world materials—elevating interfaces that feel both digital and tangible.\",\n    },\n    {\n      index: \"03\",\n      title: \"Precision\",\n      image: \"/sticky-cards/card_3.jpg\",\n      description:\n        \"Details matter. We work with intention—aligning pixels, calibrating contrast, and obsessing over every edge until it just feels right.\",\n    },\n    {\n      index: \"04\",\n      title: \"Character\",\n      image: \"/sticky-cards/card_4.jpg\",\n      description:\n        \"Interfaces should have personality. We embed small moments of play and irregularity to bring warmth, charm, and a human feel to the digital.\",\n    },\n  ];\n\n  const container = useRef(null);\n\n  useGSAP(\n    () => {\n      const stickyCards = document.querySelectorAll(\".sticky-card\");\n\n      stickyCards.forEach((card, index) => {\n        if (index < stickyCards.length - 1) {\n          ScrollTrigger.create({\n            trigger: card,\n            start: \"top top\",\n            endTrigger: stickyCards[stickyCards.length - 1],\n            end: \"top top\",\n            pin: true,\n            pinSpacing: false,\n          });\n        }\n\n        if (index < stickyCards.length - 1) {\n          ScrollTrigger.create({\n            trigger: stickyCards[index + 1],\n            start: \"top bottom\",\n            end: \"top top\",\n            onUpdate: (self) => {\n              const progress = self.progress;\n              const scale = 1 - progress * 0.25;\n              const rotation = (index % 2 === 0 ? 5 : -5) * progress;\n              const afterOpacity = progress;\n\n              gsap.set(card, {\n                scale: scale,\n                rotation: rotation,\n                \"--after-opacity\": afterOpacity,\n              });\n            },\n          });\n        }\n      });\n    },\n    { scope: container }\n  );\n\n  return (\n    <div className=\"sticky-cards\" ref={container}>\n      {stickyCardsData.map((cardData, index) => (\n        <div className=\"sticky-card\" key={index}>\n          <div className=\"sticky-card-index\">\n            <h1>{cardData.index}</h1>\n          </div>\n          <div className=\"sticky-card-content\">\n            <div className=\"sticky-card-content-wrapper\">\n              <h1 className=\"sticky-card-header\">{cardData.title}</h1>\n\n              <div className=\"sticky-card-img\">\n                <img src={cardData.image} alt=\"\" />\n              </div>\n\n              <div className=\"sticky-card-copy\">\n                <div className=\"sticky-card-copy-title\">\n                  <p>(About the state)</p>\n                </div>\n                <div className=\"sticky-card-copy-description\">\n                  <p>{cardData.description}</p>\n                </div>\n              </div>\n            </div>\n          </div>\n        </div>\n      ))}\n    </div>\n  );\n};\n\nexport default StickyCards;\n"
  }
}