{
  "title": "mukta-ova-scroll-slider",
  "code": {
    "index.html": "<!DOCTYPE html>\n<html lang=\"en\">\n  <head>\n    <meta charset=\"UTF-8\" />\n    <meta name=\"viewport\" content=\"width=device-width, initial-scale=1.0\" />\n    <title>OVA Scroll Slider | mukta</title>\n    <link rel=\"stylesheet\" href=\"/styles.css\" />\n  </head>\n  <body>\n    <nav>\n      <div class=\"logo\">\n        <p>mukta / Experiment 501</p>\n      </div>\n      <div class=\"site-info\">\n        <p>[ Scroll Motion Slider ]</p>\n      </div>\n    </nav>\n\n    <section class=\"intro\">\n      <h1>\n        Scroll to explore the rhythm of still images that move quietly between\n        story and sensation.\n      </h1>\n    </section>\n\n    <section class=\"slider\">\n      <div class=\"slider-images\">\n        <img src=\"/slider_img_1.jpg\" alt=\"Slide 1\" />\n      </div>\n\n      <div class=\"slider-title\">\n        <h1>\n          Under the soft hum of streetlights she watches the world ripple\n          through glass, her calm expression mirrored in the fragments of\n          drifting light.\n        </h1>\n      </div>\n\n      <div class=\"slider-indicator\">\n        <div class=\"slider-indices\"></div>\n\n        <div class=\"slider-progress-bar\">\n          <div class=\"slider-progress\"></div>\n        </div>\n      </div>\n    </section>\n\n    <section class=\"outro\">\n      <h1>\n        As the sequence slows the silence takes over, holding the last traces of\n        motion in the air.\n      </h1>\n    </section>\n    <script type=\"module\" src=\"/script.js\"></script>\n  </body>\n</html>\n",
    "package.json": "{\n  \"name\": \"mukta-ova-scroll-slider\",\n  \"version\": \"1.0.0\",\n  \"main\": \"index.js\",\n  \"scripts\": {\n    \"dev\": \"vite\"\n  },\n  \"keywords\": [],\n  \"author\": \"\",\n  \"license\": \"ISC\",\n  \"description\": \"\",\n  \"dependencies\": {\n    \"gsap\": \"^3.13.0\",\n    \"lenis\": \"^1.3.13\",\n    \"vite\": \"^7.1.12\"\n  }\n}\n",
    "script.js": "import gsap from \"gsap\";\nimport { ScrollTrigger } from \"gsap/ScrollTrigger\";\nimport { SplitText } from \"gsap/SplitText\";\nimport Lenis from \"lenis\";\n\ndocument.addEventListener(\"DOMContentLoaded\", () => {\n  gsap.registerPlugin(ScrollTrigger, SplitText);\n\n  const lenis = new Lenis();\n  lenis.on(\"scroll\", ScrollTrigger.update);\n  gsap.ticker.add((time) => {\n    lenis.raf(time * 1000);\n  });\n  gsap.ticker.lagSmoothing(0);\n\n  const slides = [\n    {\n      title:\n        \"Under the soft hum of streetlights she watches the world ripple through glass, her calm expression mirrored in the fragments of drifting light.\",\n      image: \"/slider_img_1.jpg\",\n    },\n    {\n      title:\n        \"A car slices through the desert, shadow chasing the wind as clouds of dust rise behind, blurring the horizon into gold and thunder.\",\n      image: \"/slider_img_2.jpg\",\n    },\n    {\n      title:\n        \"Reflections ripple across mirrored faces, each one a fragment of identity, caught between defiance, doubt, and the silence of thought.\",\n      image: \"/slider_img_3.jpg\",\n    },\n    {\n      title:\n        \"Soft light spills through the café windows as morning settles into wood and metal, capturing the rhythm of quiet human routine.\",\n      image: \"/slider_img_4.jpg\",\n    },\n    {\n      title:\n        \"Every serve becomes a battle between focus and instinct, movement flowing like rhythm as the court blurs beneath the sunlight.\",\n      image: \"/slider_img_5.jpg\",\n    },\n    {\n      title:\n        \"Amber light spills over the stage as guitars cry into smoke and shadow, where music and motion merge into pure energy.\",\n      image: \"/slider_img_6.jpg\",\n    },\n    {\n      title:\n        \"Dust erupts beneath his stride as sweat glints under floodlights, every step pushing closer to victory, grit, and pure determination.\",\n      image: \"/slider_img_7.jpg\",\n    },\n  ];\n\n  const pinDistance = window.innerHeight * slides.length;\n  const progressBar = document.querySelector(\".slider-progress\");\n  const sliderImages = document.querySelector(\".slider-images\");\n  const sliderTitle = document.querySelector(\".slider-title\");\n  const sliderIndices = document.querySelector(\".slider-indices\");\n\n  let activeSlide = 0;\n  let currentSplit = null;\n\n  function createIndices() {\n    sliderIndices.innerHTML = \"\";\n\n    slides.forEach((_, index) => {\n      const indexNum = (index + 1).toString().padStart(2, \"0\");\n      const indicatorElement = document.createElement(\"p\");\n      indicatorElement.dataset.index = index;\n      indicatorElement.innerHTML = `<span class=\"marker\"></span><span class=\"index\">${indexNum}</span>`;\n      sliderIndices.appendChild(indicatorElement);\n\n      if (index === 0) {\n        gsap.set(indicatorElement.querySelector(\".index\"), {\n          opacity: 1,\n        });\n        gsap.set(indicatorElement.querySelector(\".marker\"), {\n          scaleX: 1,\n        });\n      } else {\n        gsap.set(indicatorElement.querySelector(\".index\"), {\n          opacity: 0.35,\n        });\n        gsap.set(indicatorElement.querySelector(\".marker\"), {\n          scaleX: 0,\n        });\n      }\n    });\n  }\n\n  function animateNewSlide(index) {\n    const newSliderImage = document.createElement(\"img\");\n    newSliderImage.src = slides[index].image;\n    newSliderImage.alt = `Slide ${index + 1}`;\n\n    gsap.set(newSliderImage, {\n      opacity: 0,\n      scale: 1.1,\n    });\n\n    sliderImages.appendChild(newSliderImage);\n\n    gsap.to(newSliderImage, {\n      opacity: 1,\n      duration: 0.5,\n      ease: \"power2.out\",\n    });\n\n    gsap.to(newSliderImage, {\n      scale: 1,\n      duration: 1,\n      ease: \"power2.out\",\n    });\n\n    const allImages = sliderImages.querySelectorAll(\"img\");\n    if (allImages.length > 3) {\n      const removeCount = allImages.length - 3;\n      for (let i = 0; i < removeCount; i++) {\n        sliderImages.removeChild(allImages[i]);\n      }\n    }\n\n    animateNewTitle(index);\n    animateIndicators(index);\n  }\n\n  function animateIndicators(index) {\n    const indicators = sliderIndices.querySelectorAll(\"p\");\n\n    indicators.forEach((indicator, i) => {\n      const markerElement = indicator.querySelector(\".marker\");\n      const indexElement = indicator.querySelector(\".index\");\n\n      if (i === index) {\n        gsap.to(indexElement, {\n          opacity: 1,\n          duration: 0.3,\n          ease: \"power2.out\",\n        });\n\n        gsap.to(markerElement, {\n          scaleX: 1,\n          duration: 0.3,\n          ease: \"power2.out\",\n        });\n      } else {\n        gsap.to(indexElement, {\n          opacity: 0.5,\n          duration: 0.3,\n          ease: \"power2.out\",\n        });\n\n        gsap.to(markerElement, {\n          scaleX: 0,\n          duration: 0.3,\n          ease: \"power2.out\",\n        });\n      }\n    });\n  }\n\n  function animateNewTitle(index) {\n    if (currentSplit) {\n      currentSplit.revert();\n    }\n\n    sliderTitle.innerHTML = `<h1>${slides[index].title}</h1>`;\n\n    currentSplit = new SplitText(sliderTitle.querySelector(\"h1\"), {\n      type: \"lines\",\n      linesClass: \"line\",\n      mask: \"lines\",\n    });\n\n    gsap.set(currentSplit.lines, {\n      yPercent: 100,\n      opacity: 0,\n    });\n\n    gsap.to(currentSplit.lines, {\n      yPercent: 0,\n      opacity: 1,\n      duration: 0.75,\n      stagger: 0.1,\n      ease: \"power3.out\",\n    });\n  }\n\n  createIndices();\n\n  ScrollTrigger.create({\n    trigger: \".slider\",\n    start: \"top top\",\n    end: `+=${pinDistance}px`,\n    scrub: 1,\n    pin: true,\n    pinSpacing: true,\n    onUpdate: (self) => {\n      gsap.set(progressBar, {\n        scaleY: self.progress,\n      });\n\n      const currentSlide = Math.floor(self.progress * slides.length);\n\n      if (activeSlide !== currentSlide && currentSlide < slides.length) {\n        activeSlide = currentSlide;\n        animateNewSlide(activeSlide);\n      }\n    },\n  });\n});\n",
    "styles.css": "@import url(\"https://fonts.googleapis.com/css2?family=Geist+Mono:wght@100..900&family=Inter:ital,opsz,wght@0,14..32,100..900;1,14..32,100..900&display=swap\");\n\n* {\n  margin: 0;\n  padding: 0;\n  box-sizing: border-box;\n}\n\nbody {\n  font-family: \"Inter\", sans-serif;\n}\n\nh1 {\n  font-size: 3rem;\n  font-weight: 400;\n  letter-spacing: -0.1rem;\n  line-height: 1.2;\n}\n\np {\n  font-family: \"Geist Mono\";\n  font-weight: 400;\n  font-size: 0.85rem;\n}\n\nimg {\n  width: 100%;\n  height: 100%;\n  object-fit: cover;\n}\n\nnav {\n  position: fixed;\n  top: 0;\n  width: 100%;\n  display: flex;\n  justify-content: space-between;\n  align-items: center;\n  padding: 2rem;\n  z-index: 2;\n}\n\nnav p {\n  text-transform: uppercase;\n  font-size: 0.75rem;\n  color: #fff;\n}\n\nnav .logo {\n  border: 1px solid rgba(255, 255, 255, 0.1);\n  border-radius: 0.25rem;\n  background-color: rgba(0, 0, 0, 0.5);\n  backdrop-filter: blur(20px);\n  padding: 0.5rem 1rem;\n  overflow: hidden;\n}\n\nsection {\n  position: relative;\n  width: 100%;\n  height: 100svh;\n  overflow: hidden;\n}\n\n.intro,\n.outro {\n  padding: 2rem;\n  align-content: center;\n  background-color: #0f0f0f;\n  color: #fff;\n}\n\n.intro h1,\n.outro h1 {\n  width: 50%;\n  margin: 0 auto;\n  text-align: center;\n}\n\n.slider-images {\n  position: absolute;\n  width: 100%;\n  height: 100%;\n}\n\n.slider-images::after {\n  content: \"\";\n  position: absolute;\n  top: 0;\n  left: 0;\n  width: 100%;\n  height: 100%;\n  background-color: rgba(0, 0, 0, 0.35);\n}\n\n.slider-images img {\n  position: absolute;\n  width: 100%;\n  height: 100%;\n  transform-origin: center;\n  will-change: transform, opacity;\n}\n\n.slider-title {\n  position: absolute;\n  top: 50%;\n  left: 2rem;\n  transform: translateY(-50%);\n  width: 50%;\n  color: #fff;\n}\n\n.slider-indicator {\n  position: absolute;\n  top: 50%;\n  right: 2rem;\n  transform: translateY(-50%);\n}\n\n.slider-indices {\n  display: flex;\n  flex-direction: column;\n  gap: 1rem;\n  padding: 1rem 1.25rem;\n}\n\n.slider-indices p {\n  display: flex;\n  align-items: center;\n  gap: 1rem;\n  color: #fff;\n}\n\n.index {\n  position: relative;\n  width: 1.25rem;\n  display: flex;\n  justify-content: flex-end;\n  will-change: opacity;\n}\n\n.marker {\n  position: relative;\n  width: 0.75rem;\n  height: 1px;\n  background-color: #fff;\n  transform-origin: right;\n  will-change: transform;\n  transform: scaleX(0);\n}\n\n.slider-progress-bar {\n  position: absolute;\n  top: 0;\n  right: 0;\n  width: 1px;\n  height: 100%;\n  background-color: rgba(255, 255, 255, 0.35);\n}\n\n.slider-progress {\n  position: absolute;\n  top: 0;\n  left: 50%;\n  transform: translateX(-50%) scaleY(0);\n  width: 3px;\n  height: 100%;\n  background-color: #fff;\n  transform-origin: top;\n  will-change: transform;\n}\n\n.line {\n  position: relative;\n  display: block;\n  will-change: transform;\n}\n\n@media (max-width: 1000px) {\n  h1 {\n    font-size: 2rem;\n    letter-spacing: 0;\n  }\n\n  nav {\n    display: none;\n  }\n\n  .intro h1,\n  .outro h1 {\n    width: 100%;\n  }\n\n  .slider-title {\n    top: 5rem;\n    left: 0;\n    transform: none;\n    width: 100%;\n    padding: 2rem;\n  }\n\n  .slider-indicator {\n    top: unset;\n    transform: none;\n    bottom: 2rem;\n  }\n}\n"
  }
}